setup.py
eak_firstpypi_rand_game/__init__.py
eak_firstpypi_rand_game/random_number_generator.py
eak_firstpypi_rand_game.egg-info/PKG-INFO
eak_firstpypi_rand_game.egg-info/SOURCES.txt
eak_firstpypi_rand_game.egg-info/dependency_links.txt
eak_firstpypi_rand_game.egg-info/not-zip-safe
eak_firstpypi_rand_game.egg-info/top_level.txt