Metadata-Version: 1.0
Name: eak-firstpypi-rand-game
Version: 0.1
Summary: Random number guess game
Home-page: UNKNOWN
Author: UNKNOWN
Author-email: UNKNOWN
License: UNKNOWN
Platform: UNKNOWN
